indoxJudge/__init__.py
indoxJudge/__pycache__/__init__.cpython-312.pyc
indoxJudge/graph/__init__.py
indoxJudge/graph/visualization.py
indoxJudge/graph/__pycache__/__init__.cpython-312.pyc
indoxJudge/graph/__pycache__/visualization.cpython-312.pyc
indoxJudge/graph/assets/style.css
indoxJudge/metrics/__init__.py
indoxJudge/metrics/__pycache__/__init__.cpython-312.pyc
indoxJudge/metrics/adversarial_robustness/__init__.py
indoxJudge/metrics/adversarial_robustness/adversarialRobustness.py
indoxJudge/metrics/adversarial_robustness/template.py
indoxJudge/metrics/adversarial_robustness/__pycache__/__init__.cpython-312.pyc
indoxJudge/metrics/adversarial_robustness/__pycache__/adversarialRobustness.cpython-312.pyc
indoxJudge/metrics/adversarial_robustness/__pycache__/template.cpython-312.pyc
indoxJudge/metrics/answer_relevancy/__init__.py
indoxJudge/metrics/answer_relevancy/answerRelevancy.py
indoxJudge/metrics/answer_relevancy/template.py
indoxJudge/metrics/answer_relevancy/__pycache__/__init__.cpython-312.pyc
indoxJudge/metrics/answer_relevancy/__pycache__/answerRelevancy.cpython-312.pyc
indoxJudge/metrics/answer_relevancy/__pycache__/template.cpython-312.pyc
indoxJudge/metrics/bertscore/__init__.py
indoxJudge/metrics/bertscore/bertscore.py
indoxJudge/metrics/bertscore/__pycache__/__init__.cpython-312.pyc
indoxJudge/metrics/bertscore/__pycache__/bertscore.cpython-312.pyc
indoxJudge/metrics/bias/__init__.py
indoxJudge/metrics/bias/bias.py
indoxJudge/metrics/bias/template.py
indoxJudge/metrics/bias/__pycache__/__init__.cpython-312.pyc
indoxJudge/metrics/bias/__pycache__/bias.cpython-312.pyc
indoxJudge/metrics/bias/__pycache__/template.cpython-312.pyc
indoxJudge/metrics/bleu/__init__.py
indoxJudge/metrics/bleu/bleu.py
indoxJudge/metrics/bleu/__pycache__/__init__.cpython-312.pyc
indoxJudge/metrics/bleu/__pycache__/bleu.cpython-312.pyc
indoxJudge/metrics/contextual_relevancy/__init__.py
indoxJudge/metrics/contextual_relevancy/contextualRelevancy.py
indoxJudge-0.1.26.dist-info/LICENSE
indoxJudge-0.1.26.dist-info/METADATA
indoxJudge-0.1.26.dist-info/WHEEL
indoxJudge-0.1.26.dist-info/top_level.txt
indoxJudge-0.1.26.dist-info/RECORD
