Metadata-Version: 2.2
Name: indoxJudge
Version: 0.1.26
Summary: Indox Judge
Home-page: https://github.com/osllmai/inDox/libs/inDoxJudge
Author: osllm
Author-email: ashkan@nematifamilyfundation.onmicrosoft.com
Keywords: Evaluation,Safety Check,LLM Comparison,RAG,LLM
Classifier: Development Status :: 3 - Alpha
Classifier: Intended Audience :: Developers
Classifier: Topic :: Software Development :: Build Tools
Classifier: License :: OSI Approved :: GNU Affero General Public License v3 or later (AGPLv3+)
Classifier: Programming Language :: Python :: 3.9
Classifier: Programming Language :: Python :: 3.10
Classifier: Programming Language :: Python :: 3.11
Classifier: Programming Language :: Python :: 3.12
Requires-Python: >=3.9
License-File: LICENSE
Requires-Dist: dash
Requires-Dist: dash_bootstrap_components
Requires-Dist: dash_daq
Requires-Dist: loguru
Requires-Dist: nltk
Requires-Dist: pandas
Requires-Dist: plotly
Requires-Dist: protobuf
Requires-Dist: pydantic
Requires-Dist: requests
Requires-Dist: scikit_learn
Requires-Dist: setuptools
Requires-Dist: tenacity
Requires-Dist: tiktoken
Requires-Dist: tqdm
Requires-Dist: transformers
Requires-Dist: scikit-criteria
Requires-Dist: tomli>=2.0.1
Requires-Dist: opencv-python>=4.9.0
Requires-Dist: Shapely>=2.0.3
Requires-Dist: ipython>=7.23.1
Requires-Dist: beautifulsoup4>=4.12.3
Requires-Dist: lmdb>=1.4.1
Requires-Dist: pyclipper>=1.3.0.post5
Requires-Dist: python-docx>=1.1.0
Requires-Dist: rapidfuzz>=3.6.1
Requires-Dist: networkx>=2.8
Requires-Dist: tifffile>=2022.8.12
Requires-Dist: numpy
Requires-Dist: openpyxl
Dynamic: author
Dynamic: author-email
Dynamic: classifier
Dynamic: description
Dynamic: description-content-type
Dynamic: home-page
Dynamic: keywords
Dynamic: requires-dist
Dynamic: requires-python
Dynamic: summary
